pandas_ta/__init__.py
pandas_ta/_compat.py
pandas_ta/_typing.py
pandas_ta/candles/__init__.py
pandas_ta/candles/cdl_doji.py
pandas_ta/candles/cdl_inside.py
pandas_ta/candles/cdl_pattern.py
pandas_ta/candles/cdl_z.py
pandas_ta/candles/ha.py
pandas_ta/core.py
pandas_ta/custom.py
pandas_ta/cycles/__init__.py
pandas_ta/cycles/ebsw.py
pandas_ta/cycles/reflex.py
pandas_ta/ma.py
pandas_ta/maps.py
pandas_ta/momentum/__init__.py
pandas_ta/momentum/ao.py
pandas_ta/momentum/apo.py
pandas_ta/momentum/bias.py
pandas_ta/momentum/bop.py
pandas_ta/momentum/brar.py
pandas_ta/momentum/cci.py
pandas_ta/momentum/cfo.py
pandas_ta/momentum/cg.py
pandas_ta/momentum/cmo.py
pandas_ta/momentum/coppock.py
pandas_ta/momentum/crsi.py
pandas_ta/momentum/cti.py
pandas_ta/momentum/dm.py
pandas_ta/momentum/er.py
pandas_ta/momentum/eri.py
pandas_ta/momentum/exhc.py
pandas_ta/momentum/fisher.py
pandas_ta/momentum/inertia.py
pandas_ta/momentum/kdj.py
pandas_ta/momentum/kst.py
pandas_ta/momentum/macd.py
pandas_ta/momentum/mom.py
pandas_ta/momentum/pgo.py
pandas_ta/momentum/ppo.py
pandas_ta/momentum/psl.py
pandas_ta/momentum/qqe.py
pandas_ta/momentum/roc.py
pandas_ta/momentum/rsi.py
pandas_ta/momentum/rsx.py
pandas_ta/momentum/rvgi.py
pandas_ta/momentum/slope.py
pandas_ta/momentum/smc.py
pandas_ta/momentum/smi.py
pandas_ta/momentum/squeeze.py
pandas_ta/momentum/squeeze_pro.py
pandas_ta/momentum/stc.py
pandas_ta/momentum/stoch.py
pandas_ta/momentum/stochf.py
pandas_ta/momentum/stochrsi.py
pandas_ta/momentum/tmo.py
pandas_ta/momentum/trix.py
pandas_ta/momentum/tsi.py
pandas_ta/momentum/uo.py
pandas_ta/momentum/willr.py
pandas_ta/overlap/__init__.py
pandas_ta/overlap/alligator.py
pandas_ta/overlap/alma.py
pandas_ta/overlap/dema.py
pandas_ta/overlap/ema.py
pandas_ta/overlap/fwma.py
pandas_ta/overlap/hilo.py
pandas_ta/overlap/hl2.py
pandas_ta/overlap/hlc3.py
pandas_ta/overlap/hma.py
pandas_ta/overlap/hwma.py
pandas_ta/overlap/ichimoku.py
pandas_ta/overlap/jma.py
pandas_ta/overlap/kama.py
pandas_ta_openbb-0.4.23.dist-info/METADATA
pandas_ta_openbb-0.4.23.dist-info/WHEEL
pandas_ta_openbb-0.4.23.dist-info/licenses/LICENSE
pandas_ta_openbb-0.4.23.dist-info/RECORD
