Metadata-Version: 2.4
Name: pandas-ta-openbb
Version: 0.4.23
Summary: Fork of pandas-ta for use with NumPy 2 and OpenBB.
License: MIT
License-File: LICENSE
Author: Kevin Johnson
Author-email: appliedmathkj@gmail.com
Requires-Python: >=3.10,<4
Classifier: License :: OSI Approved :: MIT License
Classifier: Programming Language :: Python :: 3
Classifier: Programming Language :: Python :: 3.10
Classifier: Programming Language :: Python :: 3.11
Classifier: Programming Language :: Python :: 3.12
Classifier: Programming Language :: Python :: 3.13
Classifier: Programming Language :: Python :: 3.14
Provides-Extra: performance
Requires-Dist: numba (>=0.63.1,<0.64.0) ; extra == "performance"
Requires-Dist: numpy (>=1.26.4)
Requires-Dist: pandas (>=2.2.0)
Requires-Dist: scipy (>=1.15.3,<2.0.0)
Requires-Dist: statsmodels (>=0.14.0,<0.15.0)
